LICENSE.txt
MANIFEST.in
README.md
setup.cfg
setup.py
RevUtils/Aria2.py
RevUtils/General.py
RevUtils/IO.py
RevUtils/Logger.py
RevUtils/OS.py
RevUtils/PersianTools.py
RevUtils/RAR.py
RevUtils/Thread.py
RevUtils/Type.py
RevUtils/__init__.py
RevUtils.egg-info/PKG-INFO
RevUtils.egg-info/SOURCES.txt
RevUtils.egg-info/dependency_links.txt
RevUtils.egg-info/requires.txt
RevUtils.egg-info/top_level.txt
RevUtils/bin/Rar.exe
RevUtils/bin/aria2c.exe