Metadata-Version: 2.1
Name: RevUtils
Version: 2022.4.3.15.15.36.235647
Summary: Utils Created And Used By RevEngine3r
Home-page: https://github.com/RevEngine3r/RevUtilities
Author: Saeed
Author-email: RevEngine3r@Gmail.Com
License: MIT
Download-URL: https://github.com/RevEngine3r/RevUtilities/archive/refs/heads/master.zip
Keywords: RAR,RevEngine3r,Persian,Tools
Platform: UNKNOWN
Classifier: Development Status :: 3 - Alpha
Classifier: Intended Audience :: Developers
Classifier: Topic :: Software Development :: Build Tools
Classifier: License :: OSI Approved :: MIT License
Classifier: Programming Language :: Python :: 3
Classifier: Programming Language :: Python :: 3.4
Classifier: Programming Language :: Python :: 3.5
Classifier: Programming Language :: Python :: 3.6
Classifier: Programming Language :: Python :: 3.7
Classifier: Programming Language :: Python :: 3.8
Classifier: Programming Language :: Python :: 3.9
Classifier: Programming Language :: Python :: 3.10
License-File: LICENSE.txt
